supercontrast/__init__.py
supercontrast/client.py
supercontrast/metrics/__init__.py
supercontrast/metrics/metrics_calculator.py
supercontrast/metrics/metrics_enum.py
supercontrast/metrics/metrics_factory.py
supercontrast/metrics/metrics_handler.py
supercontrast/metrics/metrics_response.py
supercontrast/metrics/calculators/__init__.py
supercontrast/metrics/calculators/bleu_calculator.py
supercontrast/metrics/calculators/character_calculator.py
supercontrast/metrics/calculators/chrf_calculator.py
supercontrast/metrics/calculators/meteor_calculator.py
supercontrast/metrics/calculators/word_calculator.py
supercontrast/metrics/decorators/__init__.py
supercontrast/metrics/decorators/track_cost.py
supercontrast/metrics/decorators/track_latency.py
supercontrast/optimizer/__init__.py
supercontrast/optimizer/optimizer_enum.py
supercontrast/optimizer/optimizer_factory.py
supercontrast/optimizer/optimizer_handler.py
supercontrast/optimizer/handlers/__init__.py
supercontrast/optimizer/handlers/mock.py
supercontrast/provider/__init__.py
supercontrast/provider/provider_enum.py
supercontrast/provider/provider_factory.py
supercontrast/provider/provider_handler.py
supercontrast/provider/handlers/__init__.py
supercontrast/provider/handlers/anthropic_handler.py
supercontrast/provider/handlers/api4ai_handler.py
supercontrast/provider/handlers/aws_handler.py
supercontrast/provider/handlers/azure_handler.py
supercontrast/provider/handlers/clarifai_handler.py
supercontrast/provider/handlers/gcp_handler.py
supercontrast/provider/handlers/modern_mt_handler.py
supercontrast/provider/handlers/openai_handler.py
supercontrast/provider/handlers/sentisight_handler.py
supercontrast/task/__init__.py
supercontrast/task/task_enum.py
supercontrast/task/task_factory.py
supercontrast/task/task_handler.py
supercontrast/task/task_metadata.py
supercontrast/task/handlers/__init__.py
supercontrast/task/handlers/ocr_handler.py
supercontrast/task/handlers/sentiment_analysis_handler.py
supercontrast-0.0.2.dist-info/LICENSE
supercontrast-0.0.2.dist-info/METADATA
supercontrast-0.0.2.dist-info/WHEEL
supercontrast-0.0.2.dist-info/top_level.txt
supercontrast-0.0.2.dist-info/RECORD
