Metadata-Version: 2.1
Name: supercontrast
Version: 0.0.2
Summary: supercontrast is a package for unifying machine learning models across providers
Home-page: https://github.com/supercontrast-ai/supercontrast
Author: supercontrast
Author-email: shravan@supercontrast.com
Classifier: Programming Language :: Python :: 3
Classifier: License :: OSI Approved :: MIT License
Classifier: Operating System :: OS Independent
Requires-Python: >=3.10
License-File: LICENSE
Requires-Dist: pydantic==2.9.2
Requires-Dist: pillow==10.4.0
Requires-Dist: black==24.10.0
Requires-Dist: isort==5.13.2
Requires-Dist: pytest==8.3.3
Requires-Dist: jiwer==3.0.4
Requires-Dist: nltk==3.9.1
Requires-Dist: num2words==0.5.13
Requires-Dist: sacrebleu==2.4.3
Requires-Dist: langchain==0.3.3
Requires-Dist: langchain-anthropic==0.2.3
Requires-Dist: langchain-openai==0.2.2
Requires-Dist: boto3==1.35.38
Requires-Dist: google-api-python-client==2.149.0
Requires-Dist: google-auth-oauthlib==1.2.1
Requires-Dist: google-auth-httplib2==0.2.0
Requires-Dist: google-auth==2.35.0
Requires-Dist: google-api-core==2.21.0
Requires-Dist: google-cloud-vision==3.7.4
Requires-Dist: google-cloud-translate==3.16.0
Requires-Dist: google-cloud-speech==2.27.0
Requires-Dist: google-cloud-language==2.14.0
Requires-Dist: msrest==0.7.1
Requires-Dist: azure-ai-textanalytics==5.3.0
Requires-Dist: azure-cognitiveservices-vision-computervision==0.9.0
Requires-Dist: azure-ai-translation-text==1.0.1
Requires-Dist: azure-core==1.31.0
Requires-Dist: azure-cognitiveservices-speech==1.41.1
Requires-Dist: openai==1.51.2
